{
  "image": "LIDC-IDRI-0437_01-01-2000-NA-CHEST-35088_31028.000000-Recon 2 ACRIN LARGE-13632_slice_0001.png",
  "mask": "LIDC-IDRI-0437_01-01-2000-NA-CHEST-35088_31028.000000-Recon 2 ACRIN LARGE-13632_slice_0001_mask.png",
  "nodules": [
    {
      "nodule_id": "Nodule 002",
      "points": [
        [
          205,
          348
        ],
        [
          204,
          349
        ],
        [
          203,
          350
        ],
        [
          203,
          351
        ],
        [
          203,
          352
        ],
        [
          203,
          353
        ],
        [
          203,
          354
        ],
        [
          203,
          355
        ],
        [
          204,
          356
        ],
        [
          205,
          356
        ],
        [
          206,
          356
        ],
        [
          207,
          356
        ],
        [
          208,
          356
        ],
        [
          209,
          355
        ],
        [
          210,
          354
        ],
        [
          210,
          353
        ],
        [
          210,
          352
        ],
        [
          210,
          351
        ],
        [
          210,
          350
        ],
        [
          209,
          349
        ],
        [
          208,
          349
        ],
        [
          207,
          348
        ],
        [
          206,
          348
        ],
        [
          205,
          348
        ]
      ],
      "malignancy": "4",
      "spiculation": "1",
      "sphericity": "4",
      "margin": "5",
      "calcification": "6"
    },
    {
      "nodule_id": "59924",
      "points": [
        [
          207,
          355
        ],
        [
          208,
          354
        ],
        [
          209,
          353
        ],
        [
          209,
          352
        ],
        [
          208,
          351
        ],
        [
          208,
          350
        ],
        [
          207,
          350
        ],
        [
          206,
          349
        ],
        [
          205,
          349
        ],
        [
          205,
          350
        ],
        [
          204,
          351
        ],
        [
          204,
          352
        ],
        [
          205,
          353
        ],
        [
          206,
          354
        ],
        [
          207,
          355
        ]
      ],
      "malignancy": "1",
      "spiculation": "1",
      "sphericity": "5",
      "margin": "2",
      "calcification": "3"
    },
    {
      "nodule_id": "4",
      "points": [
        [
          208,
          350
        ],
        [
          207,
          349
        ],
        [
          206,
          349
        ],
        [
          205,
          349
        ],
        [
          204,
          349
        ],
        [
          204,
          350
        ],
        [
          203,
          351
        ],
        [
          203,
          352
        ],
        [
          204,
          353
        ],
        [
          205,
          353
        ],
        [
          206,
          354
        ],
        [
          207,
          354
        ],
        [
          208,
          353
        ],
        [
          208,
          352
        ],
        [
          208,
          351
        ],
        [
          208,
          350
        ]
      ],
      "malignancy": "1",
      "spiculation": "1",
      "sphericity": "5",
      "margin": "5",
      "calcification": "3"
    }
  ]
}