{
  "image": "LIDC-IDRI-0060_01-01-2000-NA-NA-18382_3000575.000000-NA-55115_slice_0009.png",
  "mask": "LIDC-IDRI-0060_01-01-2000-NA-NA-18382_3000575.000000-NA-55115_slice_0009_mask.png",
  "nodules": [
    {
      "nodule_id": "Nodule 002",
      "points": [
        [
          339,
          219
        ],
        [
          338,
          220
        ],
        [
          337,
          221
        ],
        [
          338,
          222
        ],
        [
          339,
          223
        ],
        [
          340,
          224
        ],
        [
          341,
          224
        ],
        [
          342,
          225
        ],
        [
          343,
          226
        ],
        [
          344,
          226
        ],
        [
          345,
          227
        ],
        [
          346,
          227
        ],
        [
          347,
          228
        ],
        [
          348,
          229
        ],
        [
          348,
          230
        ],
        [
          349,
          231
        ],
        [
          350,
          231
        ],
        [
          351,
          231
        ],
        [
          352,
          230
        ],
        [
          353,
          229
        ],
        [
          354,
          228
        ],
        [
          355,
          227
        ],
        [
          355,
          226
        ],
        [
          355,
          225
        ],
        [
          355,
          224
        ],
        [
          355,
          223
        ],
        [
          354,
          222
        ],
        [
          353,
          221
        ],
        [
          352,
          220
        ],
        [
          351,
          220
        ],
        [
          350,
          219
        ],
        [
          349,
          219
        ],
        [
          348,
          219
        ],
        [
          347,
          219
        ],
        [
          346,
          219
        ],
        [
          345,
          219
        ],
        [
          344,
          219
        ],
        [
          343,
          219
        ],
        [
          342,
          219
        ],
        [
          341,
          219
        ],
        [
          340,
          219
        ],
        [
          339,
          219
        ]
      ],
      "malignancy": "5",
      "spiculation": "3",
      "sphericity": "3",
      "margin": "3",
      "calcification": "6"
    },
    {
      "nodule_id": "IL057_130535",
      "points": [
        [
          349,
          231
        ],
        [
          350,
          230
        ],
        [
          351,
          229
        ],
        [
          352,
          228
        ],
        [
          352,
          227
        ],
        [
          352,
          226
        ],
        [
          352,
          225
        ],
        [
          351,
          224
        ],
        [
          352,
          223
        ],
        [
          352,
          222
        ],
        [
          352,
          221
        ],
        [
          352,
          220
        ],
        [
          351,
          219
        ],
        [
          350,
          219
        ],
        [
          349,
          220
        ],
        [
          348,
          220
        ],
        [
          347,
          221
        ],
        [
          347,
          222
        ],
        [
          346,
          223
        ],
        [
          345,
          223
        ],
        [
          344,
          223
        ],
        [
          343,
          224
        ],
        [
          342,
          224
        ],
        [
          342,
          225
        ],
        [
          343,
          226
        ],
        [
          343,
          227
        ],
        [
          343,
          228
        ],
        [
          343,
          229
        ],
        [
          344,
          229
        ],
        [
          345,
          229
        ],
        [
          346,
          229
        ],
        [
          347,
          230
        ],
        [
          348,
          231
        ],
        [
          349,
          231
        ]
      ],
      "malignancy": "5",
      "spiculation": "4",
      "sphericity": "4",
      "margin": "3",
      "calcification": "6"
    }
  ]
}