{
  "image": "LIDC-IDRI-0437_01-01-2000-NA-CHEST-35088_31028.000000-Recon 2 ACRIN LARGE-13632_slice_0011.png",
  "mask": "LIDC-IDRI-0437_01-01-2000-NA-CHEST-35088_31028.000000-Recon 2 ACRIN LARGE-13632_slice_0011_mask.png",
  "nodules": [
    {
      "nodule_id": "Nodule 003",
      "points": [
        [
          183,
          337
        ],
        [
          182,
          338
        ],
        [
          181,
          339
        ],
        [
          181,
          340
        ],
        [
          182,
          341
        ],
        [
          183,
          342
        ],
        [
          184,
          343
        ],
        [
          185,
          344
        ],
        [
          186,
          344
        ],
        [
          187,
          344
        ],
        [
          188,
          343
        ],
        [
          188,
          342
        ],
        [
          188,
          341
        ],
        [
          187,
          340
        ],
        [
          187,
          339
        ],
        [
          186,
          338
        ],
        [
          185,
          338
        ],
        [
          184,
          337
        ],
        [
          183,
          337
        ]
      ],
      "malignancy": "2",
      "spiculation": "1",
      "sphericity": "4",
      "margin": "5",
      "calcification": "6"
    },
    {
      "nodule_id": "52336",
      "points": [
        [
          185,
          342
        ],
        [
          186,
          341
        ],
        [
          186,
          340
        ],
        [
          186,
          339
        ],
        [
          185,
          338
        ],
        [
          184,
          338
        ],
        [
          183,
          338
        ],
        [
          182,
          339
        ],
        [
          181,
          340
        ],
        [
          182,
          341
        ],
        [
          183,
          341
        ],
        [
          184,
          342
        ],
        [
          185,
          342
        ]
      ],
      "malignancy": "1",
      "spiculation": "1",
      "sphericity": "5",
      "margin": "5",
      "calcification": "3"
    },
    {
      "nodule_id": "59936",
      "points": [
        [
          334,
          412
        ],
        [
          335,
          411
        ],
        [
          336,
          411
        ],
        [
          337,
          410
        ],
        [
          337,
          409
        ],
        [
          336,
          408
        ],
        [
          335,
          407
        ],
        [
          334,
          407
        ],
        [
          333,
          406
        ],
        [
          332,
          406
        ],
        [
          331,
          406
        ],
        [
          330,
          407
        ],
        [
          329,
          408
        ],
        [
          328,
          409
        ],
        [
          328,
          410
        ],
        [
          329,
          410
        ],
        [
          330,
          411
        ],
        [
          331,
          411
        ],
        [
          332,
          411
        ],
        [
          333,
          412
        ],
        [
          334,
          412
        ]
      ],
      "malignancy": "1",
      "spiculation": "1",
      "sphericity": "3",
      "margin": "3",
      "calcification": "6"
    },
    {
      "nodule_id": "59933",
      "points": [
        [
          185,
          342
        ],
        [
          186,
          341
        ],
        [
          186,
          340
        ],
        [
          186,
          339
        ],
        [
          185,
          338
        ],
        [
          184,
          337
        ],
        [
          183,
          337
        ],
        [
          182,
          338
        ],
        [
          182,
          339
        ],
        [
          181,
          340
        ],
        [
          181,
          341
        ],
        [
          182,
          342
        ],
        [
          183,
          342
        ],
        [
          184,
          342
        ],
        [
          185,
          342
        ]
      ],
      "malignancy": "1",
      "spiculation": "1",
      "sphericity": "3",
      "margin": "5",
      "calcification": "3"
    },
    {
      "nodule_id": "1",
      "points": [
        [
          184,
          337
        ],
        [
          183,
          338
        ],
        [
          182,
          338
        ],
        [
          182,
          339
        ],
        [
          182,
          340
        ],
        [
          182,
          341
        ],
        [
          183,
          342
        ],
        [
          184,
          342
        ],
        [
          185,
          343
        ],
        [
          186,
          343
        ],
        [
          187,
          342
        ],
        [
          187,
          341
        ],
        [
          187,
          340
        ],
        [
          187,
          339
        ],
        [
          186,
          338
        ],
        [
          186,
          337
        ],
        [
          185,
          337
        ],
        [
          184,
          337
        ]
      ],
      "malignancy": "1",
      "spiculation": "1",
      "sphericity": "5",
      "margin": "5",
      "calcification": "3"
    }
  ]
}