{
  "image": "LIDC-IDRI-0186_01-01-2000-NA-CT LUNG MED PLEURA-37287_3.000000-Recon 2 CHEST-74757_slice_0019.png",
  "mask": "LIDC-IDRI-0186_01-01-2000-NA-CT LUNG MED PLEURA-37287_3.000000-Recon 2 CHEST-74757_slice_0019_mask.png",
  "nodules": [
    {
      "nodule_id": "115429",
      "points": [
        [
          341,
          130
        ],
        [
          342,
          129
        ],
        [
          342,
          128
        ],
        [
          342,
          127
        ],
        [
          342,
          126
        ],
        [
          343,
          125
        ],
        [
          343,
          124
        ],
        [
          342,
          123
        ],
        [
          342,
          122
        ],
        [
          341,
          121
        ],
        [
          340,
          121
        ],
        [
          339,
          121
        ],
        [
          338,
          121
        ],
        [
          337,
          122
        ],
        [
          336,
          123
        ],
        [
          336,
          124
        ],
        [
          336,
          125
        ],
        [
          336,
          126
        ],
        [
          337,
          127
        ],
        [
          337,
          128
        ],
        [
          338,
          129
        ],
        [
          339,
          129
        ],
        [
          340,
          130
        ],
        [
          341,
          130
        ]
      ],
      "malignancy": "1",
      "spiculation": "1",
      "sphericity": "4",
      "margin": "5",
      "calcification": "3"
    },
    {
      "nodule_id": "135724",
      "points": [
        [
          340,
          129
        ],
        [
          341,
          128
        ],
        [
          342,
          127
        ],
        [
          342,
          126
        ],
        [
          342,
          125
        ],
        [
          342,
          124
        ],
        [
          342,
          123
        ],
        [
          341,
          122
        ],
        [
          340,
          121
        ],
        [
          339,
          121
        ],
        [
          338,
          122
        ],
        [
          337,
          123
        ],
        [
          337,
          124
        ],
        [
          337,
          125
        ],
        [
          337,
          126
        ],
        [
          337,
          127
        ],
        [
          338,
          128
        ],
        [
          339,
          128
        ],
        [
          340,
          129
        ]
      ],
      "malignancy": "1",
      "spiculation": "1",
      "sphericity": "5",
      "margin": "5",
      "calcification": "3"
    }
  ]
}