{
  "image": "LIDC-IDRI-0340_01-01-2000-NA-NA-53729_30356.000000-NA-14832_slice_0047.png",
  "mask": "LIDC-IDRI-0340_01-01-2000-NA-NA-53729_30356.000000-NA-14832_slice_0047_mask.png",
  "nodules": [
    {
      "nodule_id": "0",
      "points": [
        [
          399,
          360
        ],
        [
          399,
          361
        ],
        [
          399,
          362
        ],
        [
          399,
          363
        ],
        [
          399,
          364
        ],
        [
          399,
          365
        ],
        [
          400,
          365
        ],
        [
          401,
          365
        ],
        [
          400,
          364
        ],
        [
          400,
          363
        ],
        [
          400,
          362
        ],
        [
          399,
          360
        ]
      ],
      "malignancy": "2",
      "spiculation": "2",
      "sphericity": "2",
      "margin": "4",
      "calcification": "6"
    }
  ]
}