{
  "image": "LIDC-IDRI-0384_01-01-2000-NA-CHEST-72716_30918.000000-Recon 2 ACRIN LARGE-65567_slice_0008.png",
  "mask": "LIDC-IDRI-0384_01-01-2000-NA-CHEST-72716_30918.000000-Recon 2 ACRIN LARGE-65567_slice_0008_mask.png",
  "nodules": [
    {
      "nodule_id": "2",
      "points": [
        [
          191,
          299
        ],
        [
          191,
          298
        ],
        [
          191,
          297
        ],
        [
          191,
          296
        ],
        [
          192,
          295
        ],
        [
          192,
          294
        ],
        [
          193,
          293
        ],
        [
          194,
          293
        ],
        [
          195,
          294
        ],
        [
          196,
          294
        ],
        [
          197,
          295
        ],
        [
          198,
          296
        ],
        [
          199,
          297
        ],
        [
          200,
          297
        ],
        [
          199,
          298
        ],
        [
          198,
          299
        ],
        [
          197,
          300
        ],
        [
          196,
          300
        ],
        [
          195,
          300
        ],
        [
          194,
          300
        ],
        [
          193,
          300
        ],
        [
          192,
          300
        ],
        [
          191,
          299
        ]
      ],
      "malignancy": "2",
      "spiculation": "1",
      "sphericity": "3",
      "margin": "4",
      "calcification": "6"
    }
  ]
}