{
  "image": "LIDC-IDRI-0061_01-01-2000-NA-NA-64840_3000560.000000-NA-47886_slice_0027.png",
  "mask": "LIDC-IDRI-0061_01-01-2000-NA-NA-64840_3000560.000000-NA-47886_slice_0027_mask.png",
  "nodules": [
    {
      "nodule_id": "4",
      "points": [
        [
          228,
          310
        ],
        [
          228,
          309
        ],
        [
          229,
          308
        ],
        [
          230,
          307
        ],
        [
          230,
          306
        ],
        [
          231,
          305
        ],
        [
          231,
          304
        ],
        [
          232,
          303
        ],
        [
          233,
          303
        ],
        [
          234,
          302
        ],
        [
          235,
          302
        ],
        [
          236,
          301
        ],
        [
          237,
          301
        ],
        [
          238,
          301
        ],
        [
          238,
          300
        ],
        [
          239,
          301
        ],
        [
          240,
          301
        ],
        [
          241,
          302
        ],
        [
          242,
          302
        ],
        [
          243,
          302
        ],
        [
          243,
          303
        ],
        [
          244,
          304
        ],
        [
          245,
          305
        ],
        [
          246,
          306
        ],
        [
          247,
          307
        ],
        [
          247,
          308
        ],
        [
          248,
          309
        ],
        [
          249,
          310
        ],
        [
          249,
          311
        ],
        [
          249,
          312
        ],
        [
          249,
          313
        ],
        [
          249,
          314
        ],
        [
          249,
          315
        ],
        [
          248,
          316
        ],
        [
          248,
          317
        ],
        [
          247,
          318
        ],
        [
          247,
          319
        ],
        [
          246,
          320
        ],
        [
          246,
          321
        ],
        [
          245,
          322
        ],
        [
          244,
          323
        ],
        [
          243,
          324
        ],
        [
          242,
          325
        ],
        [
          241,
          326
        ],
        [
          240,
          327
        ],
        [
          239,
          327
        ],
        [
          238,
          327
        ],
        [
          237,
          327
        ],
        [
          236,
          326
        ],
        [
          235,
          326
        ],
        [
          234,
          326
        ],
        [
          233,
          325
        ],
        [
          232,
          324
        ],
        [
          231,
          323
        ],
        [
          230,
          323
        ],
        [
          230,
          322
        ],
        [
          229,
          321
        ],
        [
          229,
          320
        ],
        [
          228,
          319
        ],
        [
          227,
          318
        ],
        [
          227,
          317
        ],
        [
          227,
          316
        ],
        [
          227,
          315
        ],
        [
          227,
          314
        ],
        [
          227,
          313
        ],
        [
          227,
          312
        ],
        [
          227,
          311
        ],
        [
          227,
          310
        ],
        [
          228,
          310
        ]
      ],
      "malignancy": "2",
      "spiculation": "1",
      "sphericity": "5",
      "margin": "5",
      "calcification": "6"
    }
  ]
}